collectivecrossing/__init__.py
collectivecrossing/actions.py
collectivecrossing/collectivecrossing.py
collectivecrossing/configs.py
collectivecrossing/observation_configs.py
collectivecrossing/observations.py
collectivecrossing/rendering.py
collectivecrossing/reward_configs.py
collectivecrossing/rewards.py
collectivecrossing/terminated_configs.py
collectivecrossing/terminateds.py
collectivecrossing/truncated_configs.py
collectivecrossing/truncateds.py
collectivecrossing/types.py
collectivecrossing/utils/geometry.py
collectivecrossing/utils/pydantic.py
collectivecrossing-0.1.3.dist-info/METADATA
collectivecrossing-0.1.3.dist-info/WHEEL
collectivecrossing-0.1.3.dist-info/licenses/LICENSE
collectivecrossing-0.1.3.dist-info/RECORD
