Metadata-Version: 2.4
Name: collectivecrossing
Version: 0.1.3
Summary: A multi-agent reinforcement learning environment for probing the overlap of MARL and social sciences
Author-email: "Nima H. Siboni" <semi.ergodic@gmail.com>
License-File: LICENSE
Keywords: collective-behavior,gymnasium,marl,multi-agent,reinforcement-learning,rl,social-sciences
Requires-Python: <3.14,>=3.10
Requires-Dist: gymnasium>=0.29.0
Requires-Dist: matplotlib>=3.7.0
Requires-Dist: numpy>=1.24.0
Requires-Dist: pydantic>=2.11.7
Requires-Dist: ray[rllib]==2.49.2
